example_packg/__init__.py
example_packg/helloworld.py
example_packg-0.0.1.dist-info/METADATA
example_packg-0.0.1.dist-info/WHEEL
example_packg-0.0.1.dist-info/top_level.txt
example_packg-0.0.1.dist-info/RECORD
